log_by_format/__init__.py
log_by_format/logger.py
log_by_format-0.1.dist-info/METADATA
log_by_format-0.1.dist-info/WHEEL
log_by_format-0.1.dist-info/top_level.txt
log_by_format-0.1.dist-info/RECORD
